rs2/BaseModel.py
rs2/Units.py
rs2/__init__.py
rs2/_common/Client.py
rs2/_common/ProxyObject.py
rs2/_common/__init__.py
rs2/_common/documentProxy.py
rs2/interpreter/InterpreterEnums.py
rs2/interpreter/InterpreterGraphEnums.py
rs2/interpreter/InterpreterModel.py
rs2/interpreter/RS2Interpreter.py
rs2/interpreter/_UtilityResult.py
rs2/interpreter/__init__.py
rs2/interpreter/queryResults/HistoryQueryResults.py
rs2/interpreter/queryResults/MaterialQueryResults.py
rs2/interpreter/queryResults/MeshResults.py
rs2/interpreter/queryResults/TimeQueryResults.py
rs2/interpreter/queryResults/__init__.py
rs2/interpreter/supportResults/BoltResult.py
rs2/interpreter/supportResults/CompositeResult.py
rs2/interpreter/supportResults/JointResult.py
rs2/interpreter/supportResults/LinerResult.py
rs2/interpreter/supportResults/__init__.py
rs2/modeler/Model.py
rs2/modeler/RS2Modeler.py
rs2/modeler/__init__.py
rs2/modeler/managed_properties/GanFunctions.py
rs2/modeler/managed_properties/material/strength/GeneralizedHoekBrown.py
rs2/modeler/managed_properties/material/strength/JointedGeneralizedHoekBrown.py
rs2/modeler/properties/AbsoluteStageFactorGettersInterface.py
rs2/modeler/properties/AbsoluteStageFactorInterface.py
rs2/modeler/properties/CompositeProperty.py
rs2/modeler/properties/DiscreteFunction.py
rs2/modeler/properties/HydroDistributionFunction.py
rs2/modeler/properties/MaterialJoint.py
rs2/modeler/properties/MaterialJointOptions.py
rs2/modeler/properties/PropertyEnums.py
rs2/modeler/properties/RelativeStageFactorInterface.py
rs2/modeler/properties/ShearNormalFunction.py
rs2/modeler/properties/SnowdenAnisotropicFunction.py
rs2/modeler/properties/StructuralInterface.py
rs2/modeler/properties/UserDefinedWaterMode.py
rs2/modeler/properties/__init__.py
rs2/modeler/properties/propertyProxy.py
rs2/modeler/properties/bolt/Bolt.py
rs2/modeler/properties/bolt/EndAnchored.py
rs2/modeler/properties/bolt/FullyBonded.py
rs2/modeler/properties/bolt/PlainStrandCable.py
rs2scripting-11.27.0.dist-info/licenses/License.txt
rs2scripting-11.27.0.dist-info/METADATA
rs2scripting-11.27.0.dist-info/WHEEL
rs2scripting-11.27.0.dist-info/top_level.txt
rs2scripting-11.27.0.dist-info/RECORD
