Metadata-Version: 2.4
Name: RS2Scripting
Version: 11.27.0
Summary: Client library for interacting with RS2 through python
Author: Rocscience
License-Expression: MIT
Project-URL: Homepage, https://www.rocscience.com/software/rs2
Project-URL: Documentation, https://www.rocscience.com/help/rs2/overview
Keywords: Rocscience,RS2,Scripting,RocScript,Geotechnical,Finite Element Analysis,FEM,2D
Classifier: Programming Language :: Python :: 3
Classifier: Topic :: Scientific/Engineering
Requires-Python: >=3.7
License-File: License.txt
Requires-Dist: rsmessages==0.0.2
Dynamic: license-file
